score.css-0.3.3-py3.7-nspkg.pth
score/css/__init__.py
score/css/_init.py
score.css-0.3.3.dist-info/COPYING.LESSER.txt
score.css-0.3.3.dist-info/METADATA
score.css-0.3.3.dist-info/WHEEL
score.css-0.3.3.dist-info/namespace_packages.txt
score.css-0.3.3.dist-info/top_level.txt
score.css-0.3.3.dist-info/RECORD
